.hgignore
CHANGES.txt
LICENSE.txt
README.txt
bootstrap.py
buildout.cfg
setup.py
js/__init__.py
js.sammy.egg-info/PKG-INFO
js.sammy.egg-info/SOURCES.txt
js.sammy.egg-info/dependency_links.txt
js.sammy.egg-info/entry_points.txt
js.sammy.egg-info/namespace_packages.txt
js.sammy.egg-info/not-zip-safe
js.sammy.egg-info/requires.txt
js.sammy.egg-info/top_level.txt
js/sammy/__init__.py
js/sammy/test_sammy.js.txt
js/sammy/resources/README.txt
js/sammy/resources/sammy.js
js/sammy/resources/sammy.min.js