Metadata-Version: 1.0
Name: js.sammy
Version: 0.6.3
Summary: Fanstatic packaging of Sammy.js
Home-page: UNKNOWN
Author: Fanstatic Developers
Author-email: fanstatic@googlegroups.com
License: BSD
Platform: UNKNOWN
